MANIFEST.in
README.md
setup.py
taggercli/__init__.py
taggercli/main.py
taggercli.egg-info/PKG-INFO
taggercli.egg-info/SOURCES.txt
taggercli.egg-info/dependency_links.txt
taggercli.egg-info/entry_points.txt
taggercli.egg-info/requires.txt
taggercli.egg-info/top_level.txt
taggercli/commands/__init__.py
taggercli/commands/config.py
taggercli/commands/exceptions.py
taggercli/commands/report.py
taggercli/commands/tag.py
taggercli/commands/util.py
taggercli/config/__init__.py
taggercli/config/config.py
taggercli/config/exceptions.py
taggercli/templates/template_report.html