Metadata-Version: 2.1
Name: taggercli
Version: 1.0.0
Summary: CLI tool for analyzing AWS tagging schemas and applying them
Home-page: https://github.com/IT-EXPERTS-AT/tagger
Author: IT-experts
Author-email: github@it-experts.at
License: License :: OSI Approved :: Apache Software License
Keywords: AWS,AWS tags,CLI,tags,tag,tagging,AWS management
Platform: UNKNOWN
Classifier: Operating System :: OS Independent
Classifier: License :: OSI Approved :: Apache Software License
Classifier: Programming Language :: Python :: 3.8
Provides-Extra: dev
